phasellm/__init__.py
phasellm/agents.py
phasellm/configurations.py
phasellm/configurations_utils.py
phasellm/eval.py
phasellm/exceptions.py
phasellm/html.py
phasellm/llms.py
phasellm/llms_utils.py
phasellm/logging.py
phasellm/types.py
tests/__init__.py
tests/release_checklist_code.py
tests/utils.py
tests/e2e/__init__.py
tests/e2e/agents/__init__.py
tests/e2e/agents/test_e2e_agents.py
tests/e2e/llms/__init__.py
tests/e2e/llms/test_e2e_llms.py
tests/e2e/llms/utils.py
tests/e2e/sse/__init__.py
tests/e2e/sse/test_e2e_sse.py
tests/unit/__init__.py
tests/unit/agents/__init__.py
tests/unit/agents/test_agents.py
tests/unit/llms/__init__.py
tests/unit/llms/test_llms.py
tests-non-deterministic/__init__.py
tests-non-deterministic/llms/__init__.py
tests-non-deterministic/llms/test_llms.py
phasellm-0.0.25.dist-info/LICENSE
phasellm-0.0.25.dist-info/METADATA
phasellm-0.0.25.dist-info/WHEEL
phasellm-0.0.25.dist-info/top_level.txt
phasellm-0.0.25.dist-info/RECORD
